actinia_processing_lib/__init__.py
actinia_processing_lib/ephemeral_processing.py
actinia_processing_lib/ephemeral_processing_with_export.py
actinia_processing_lib/exceptions.py
actinia_processing_lib/persistent_processing.py
actinia_processing_lib/utils.py
actinia_processing_lib-1.1.1.dist-info/licenses/LICENSE.txt
actinia_processing_lib-1.1.1.dist-info/METADATA
actinia_processing_lib-1.1.1.dist-info/WHEEL
actinia_processing_lib-1.1.1.dist-info/top_level.txt
actinia_processing_lib-1.1.1.dist-info/RECORD
